ctypespec/__init__.py
ctypespec/_version.py
ctypespec/ast_parser.py
ctypespec/cdecl_parser.py
ctypespec/clang_helper.py
ctypespec/ctype2dataframe.py
ctypespec/ctype_helper.py
ctypespec-0.1.9.dist-info/METADATA
ctypespec-0.1.9.dist-info/WHEEL
ctypespec-0.1.9.dist-info/licenses/LICENSE
ctypespec-0.1.9.dist-info/RECORD
